example_pkg/__init__.py
animalcrossing-0.0.1.dist-info/LICENCE
animalcrossing-0.0.1.dist-info/METADATA
animalcrossing-0.0.1.dist-info/WHEEL
animalcrossing-0.0.1.dist-info/top_level.txt
animalcrossing-0.0.1.dist-info/RECORD
