Metadata-Version: 2.1
Name: animalcrossing
Version: 0.0.1
Summary: Animal crossing for computer vision
Home-page: https://github.com/pypa/sampleproject
Author: Cortez Ethridge
Author-email: cortez.ethridge@gmail.com
License: UNKNOWN
Platform: UNKNOWN
Classifier: Programming Language :: Python :: 3
Classifier: License :: OSI Approved :: MIT License
Classifier: Operating System :: OS Independent
Requires-Python: >=3.6
Requires-Dist: pandas
Requires-Dist: ipython
